smarttextdecorator/__init__.py
smarttextdecorator/decorators.py
smarttextdecorator-0.1.3.dist-info/licenses/LICENSE
smarttextdecorator-0.1.3.dist-info/METADATA
smarttextdecorator-0.1.3.dist-info/WHEEL
smarttextdecorator-0.1.3.dist-info/top_level.txt
smarttextdecorator-0.1.3.dist-info/RECORD
