Metadata-Version: 2.4
Name: smarttextdecorator
Version: 0.1.3
Summary: A cross-platform library for decorating strings and displaying them beautifully in the console. Generates and displays lines to the full width of the console with the specified text and a placeholder character. Generates and displays a line with the specified text, decorated at the top and bottom with filler characters along the length of the line. Use for beautiful design of console applications.
Home-page: https://github.com/smartlegionlab/smarttextdecorator/
Author: A.A. Suvorov
Author-email: smartlegiondev@gmail.com
License: BSD 3-Clause License
Project-URL: Documentation, https://github.com/smartlegionlab/smarttextdecorator/blob/master/README.md
Project-URL: Release notes, https://github.com/smartlegionlab/smarttextdecorator/releases
Keywords: text decorator,smartlegionlab,smart printer,smartprinter
Classifier: Development Status :: 5 - Production/Stable
Classifier: License :: OSI Approved :: BSD License
Classifier: Natural Language :: English
Classifier: Operating System :: OS Independent
Classifier: Operating System :: Microsoft :: Windows
Classifier: Operating System :: POSIX :: Linux
Classifier: Programming Language :: Python :: 3 :: Only
Classifier: Topic :: Software Development :: Libraries :: Python Modules
Requires-Python: >=3.6
License-File: LICENSE
Dynamic: license-file
